Topsis_Aayush_102003745/__init__.py
Topsis_Aayush_102003745-0.0.1.dist-info/LICENSE
Topsis_Aayush_102003745-0.0.1.dist-info/METADATA
Topsis_Aayush_102003745-0.0.1.dist-info/WHEEL
Topsis_Aayush_102003745-0.0.1.dist-info/top_level.txt
Topsis_Aayush_102003745-0.0.1.dist-info/RECORD
