Metadata-Version: 2.1
Name: Topsis-Aayush-102003745
Version: 0.0.1
Summary: Streaming video data via networks
Author: Aayush Asrey
Author-email: aasrey_be20@thapar.edu
License: UNKNOWN
Platform: UNKNOWN
License-File: LICENSE
Requires-Dist: pandas
